Changelog.txt
LICENSE.txt
MANIFEST.in
Makefile
README.txt
distribute_setup.py
epydoc.css
setup.py
docs/Makefile
docs/source/conf.py
docs/source/index.rst
pyzmail/__init__.py
pyzmail/generate.py
pyzmail/parse.py
pyzmail/utils.py
pyzmail/version.py
pyzmail/tests/__init__.py
pyzmail/tests/test_both.py
pyzmail/tests/test_generate.py
pyzmail/tests/test_parse.py
pyzmail/tests/test_send.py
pyzmail/tests/test_utils.py
pyzmail36.egg-info/PKG-INFO
pyzmail36.egg-info/SOURCES.txt
pyzmail36.egg-info/dependency_links.txt
pyzmail36.egg-info/requires.txt
pyzmail36.egg-info/top_level.txt
scripts/pyzinfomail
scripts/pyzsendmail